rebop-0.9.4.dist-info/METADATA
rebop-0.9.4.dist-info/WHEEL
rebop-0.9.4.dist-info/licenses/LICENSE
rebop/__init__.py
rebop/_lib.cpython-313-x86_64-linux-gnu.so
rebop/gillespie.py
rebop/py.typed
rebop-0.9.4.dist-info/RECORD
